pierone/__init__.py
pierone/__main__.py
pierone/api.py
pierone/cli.py
pierone/credhelper.py
pierone/exceptions.py
pierone/types.py
pierone/ui.py
pierone/utils.py
pierone/validators.py
stups_pierone-1.1.56.dist-info/LICENSE
stups_pierone-1.1.56.dist-info/METADATA
stups_pierone-1.1.56.dist-info/WHEEL
stups_pierone-1.1.56.dist-info/entry_points.txt
stups_pierone-1.1.56.dist-info/top_level.txt
stups_pierone-1.1.56.dist-info/RECORD
