Metadata-Version: 2.1
Name: stups-pierone
Version: 1.1.56
Summary: Pier One Docker registry CLI
Home-page: https://github.com/zalando-stups/pierone-cli
Author: Henning Jacobs
Author-email: henning.jacobs@zalando.de
License: Apache License 2.0
Keywords: pier one docker registry
Classifier: Development Status :: 4 - Beta
Classifier: Environment :: Console
Classifier: Intended Audience :: Developers
Classifier: Intended Audience :: System Administrators
Classifier: License :: OSI Approved :: Apache Software License
Classifier: Operating System :: POSIX :: Linux
Classifier: Programming Language :: Python
Classifier: Programming Language :: Python :: 3.4
Classifier: Programming Language :: Python :: Implementation :: CPython
License-File: LICENSE
Requires-Dist: clickclick >=1.0
Requires-Dist: requests
Requires-Dist: stups-zign >=1.0.22
Requires-Dist: stups-cli-support
